amd/__init__.py
amd/_emd.py
amd/_nearest_neighbors.py
amd/_private.py
amd/_types.py
amd/atomic_masses.json
amd/atomic_numbers.json
amd/calculate.py
amd/compare.py
amd/globals_.py
amd/io.py
amd/periodicset.py
amd/reconstruct.py
amd/utils.py
average_minimum_distance-1.6.1.dist-info/licenses/LICENSE
average_minimum_distance-1.6.1.dist-info/METADATA
average_minimum_distance-1.6.1.dist-info/WHEEL
average_minimum_distance-1.6.1.dist-info/top_level.txt
average_minimum_distance-1.6.1.dist-info/RECORD
