Metadata-Version: 2.4
Name: average-minimum-distance
Version: 1.6.1
Summary: Descriptors of crystals based on geometry (isometry invariants).
Author-email: Daniel Widdowson <dwiddo@liverpool.ac.uk>
Maintainer-email: Daniel Widdowson <dwiddo@liverpool.ac.uk>
Project-URL: Documentation, https://average-minimum-distance.readthedocs.io/en/latest/
Project-URL: Source Code, https://github.com/dwiddo/average-minimum-distance/
Project-URL: Changelog, https://github.com/dwiddo/average-minimum-distance/blob/master/CHANGELOG.md
Keywords: isometry invariant,geometric data science,crystal,amd,pdd,similarity,average,minimum,pointwise,distance,cif
Classifier: Development Status :: 4 - Beta
Classifier: Intended Audience :: Science/Research
Classifier: Natural Language :: English
Classifier: Operating System :: OS Independent
Classifier: Programming Language :: Python
Classifier: Programming Language :: Python :: 3
Classifier: Programming Language :: Python :: 3 :: Only
Classifier: Programming Language :: Python :: 3.9
Classifier: Programming Language :: Python :: 3.10
Classifier: Programming Language :: Python :: 3.11
Classifier: Programming Language :: Python :: 3.12
Classifier: Programming Language :: Python :: 3.13
Classifier: Topic :: Scientific/Engineering :: Chemistry
Classifier: Topic :: Scientific/Engineering :: Mathematics
Requires-Python: >=3.9
License-File: LICENSE
Requires-Dist: gemmi>=0.5.8
Requires-Dist: joblib>=1.1.0
Requires-Dist: numba>=0.55.2
Requires-Dist: numpy>=1.21
Requires-Dist: pandas>=1.2.5
Requires-Dist: scikit-learn>=1.0.0
Requires-Dist: scipy>=1.6.1
Requires-Dist: tqdm>=4.1.0
Provides-Extra: ccdc
Requires-Dist: csd-python-api; extra == "ccdc"
Provides-Extra: pymatgen
Requires-Dist: pymatgen; extra == "pymatgen"
Provides-Extra: dev
Requires-Dist: pytest; extra == "dev"
Provides-Extra: docs
Requires-Dist: mock<=5.2.0; extra == "docs"
Dynamic: license-file
